allure_env_builder/__init__.py
allure_env_builder/builder.py
allure_env_builder/py.typed
allure_env_builder-1.0.0.dist-info/LICENSE
allure_env_builder-1.0.0.dist-info/METADATA
allure_env_builder-1.0.0.dist-info/WHEEL
allure_env_builder-1.0.0.dist-info/top_level.txt
allure_env_builder-1.0.0.dist-info/RECORD
