Metadata-Version: 2.1
Name: allure-env-builder
Version: 1.0.0
Summary: Библиотека для создания файла с переменными окружения для allure-report-service
Home-page: https://github.com/Gwinkamp/allure-env-builder
Author: Gwinkamp
License: MIT
Keywords: tools
Classifier: Topic :: Utilities
Requires-Python: >=3.10
License-File: LICENSE
